{
  "matchId": "852840676510092",
  "timestamp": 1784257921,
  "timeAgo": {
    "number": 1,
    "unit": "hours"
  },
  "clubs": {
    "127516": {
      "date": "1784257920",
      "gameNumber": "0",
      "goals": "1",
      "goalsAgainst": "1",
      "losses": "0",
      "matchType": "1",
      "result": "4",
      "score": "1",
      "season_id": "0",
      "TEAM": "99060207",
      "ties": "1",
      "winnerByDnf": "0",
      "wins": "0",
      "details": {
        "name": "Meat Commission",
        "clubId": 127516,
        "regionId": 4543827,
        "teamId": 243,
        "customKit": {
          "stadName": "Slaughterhouse",
          "kitId": "1990656",
          "seasonalTeamId": "131397",
          "seasonalKitId": "1076404224",
          "selectedKitType": "1",
          "customKitId": "7853",
          "customAwayKitId": "7532",
          "customThirdKitId": "7629",
          "customKeeperKitId": "5020",
          "kitColor1": "396864",
          "kitColor2": "15245824",
          "kitColor3": "16687883",
          "kitColor4": "15245824",
          "kitAColor1": "6887227",
          "kitAColor2": "396864",
          "kitAColor3": "15921906",
          "kitAColor4": "15921906",
          "kitThrdColor1": "396864",
          "kitThrdColor2": "15245824",
          "kitThrdColor3": "15921906",
          "kitThrdColor4": "15245824",
          "dCustomKit": "0",
          "crestColor": "16777215",
          "crestAssetId": "99060207"
        }
      }
    },
    "727011": {
      "date": "1784257920",
      "gameNumber": "0",
      "goals": "1",
      "goalsAgainst": "1",
      "losses": "0",
      "matchType": "1",
      "result": "4",
      "score": "1",
      "season_id": "0",
      "TEAM": "1352",
      "ties": "1",
      "winnerByDnf": "0",
      "wins": "0",
      "details": {
        "name": "Daralagjazsky",
        "clubId": 727011,
        "regionId": 1163219762,
        "teamId": 1352,
        "customKit": {
          "stadName": "The Jungle",
          "kitId": "11075584",
          "seasonalTeamId": "131397",
          "seasonalKitId": "1076404224",
          "selectedKitType": "0",
          "customKitId": "7646",
          "customAwayKitId": "7648",
          "customThirdKitId": "7605",
          "customKeeperKitId": "5016",
          "kitColor1": "1713203",
          "kitColor2": "11194602",
          "kitColor3": "11319490",
          "kitColor4": "12702174",
          "kitAColor1": "15921906",
          "kitAColor2": "14655653",
          "kitAColor3": "11194602",
          "kitAColor4": "14655653",
          "kitThrdColor1": "12706617",
          "kitThrdColor2": "16774144",
          "kitThrdColor3": "592397",
          "kitThrdColor4": "592397",
          "dCustomKit": "1",
          "crestColor": "0",
          "crestAssetId": "99160109"
        }
      }
    }
  },
  "players": {
    "727011": {
      "171634279": {
        "archetypeid": "12",
        "assists": "0",
        "ballDiveSaves": "0",
        "cleansheetsany": "0",
        "cleansheetsdef": "0",
        "cleansheetsgk": "0",
        "crossSaves": "0",
        "gameTime": "5468",
        "goals": "1",
        "goalsconceded": "1",
        "goodDirectionSaves": "0",
        "losses": "0",
        "match_event_aggregate_0": "1:3,101:2,107:3,111:19,112:1,114:1,124:1,13:2,131:1,143:2,152:3,157:1,163:2,174:17,175:6,176:10,177:4,182:1,183:2,202:1,211:3,212:2,214:1,215:17,216:2,217:2,219:2,24:13,25:1,26:4,265:1,30:5,32:10,33:1,34:2,35:1,37:1,6:1,97:6",
        "match_event_aggregate_1": "",
        "match_event_aggregate_2": "",
        "match_event_aggregate_3": "",
        "mom": "0",
        "namespace": "1",
        "parrySaves": "0",
        "passattempts": "20",
        "passesmade": "17",
        "pos": "forward",
        "punchSaves": "0",
        "rating": "7.50",
        "realtimegame": "887",
        "realtimeidle": "12",
        "redcards": "0",
        "reflexSaves": "0",
        "saves": "0",
        "SCORE": "1",
        "secondsPlayed": "5468",
        "shots": "2",
        "tackleattempts": "4",
        "tacklesmade": "0",
        "userResult": "0",
        "vproattr": "NH",
        "vprohackreason": "0",
        "wins": "0",
        "playername": "Manther04"
      },
      "179989021": {
        "archetypeid": "11",
        "assists": "0",
        "ballDiveSaves": "0",
        "cleansheetsany": "0",
        "cleansheetsdef": "0",
        "cleansheetsgk": "0",
        "crossSaves": "0",
        "gameTime": "5468",
        "goals": "0",
        "goalsconceded": "1",
        "goodDirectionSaves": "0",
        "losses": "0",
        "match_event_aggregate_0": "1:3,100:2,102:23,105:1,106:2,111:2,112:1,114:1,13:1,143:13,145:2,151:1,152:4,153:1,157:1,163:1,174:18,175:9,176:8,177:3,178:1,182:11,183:2,19:1,211:1,215:24,216:7,217:1,218:1,219:25,24:13,25:4,26:7,28:4,29:2,30:8,31:4,32:6,34:10,35:3,37:1,6:1,97:11",
        "match_event_aggregate_1": "",
        "match_event_aggregate_2": "",
        "match_event_aggregate_3": "",
        "mom": "0",
        "namespace": "2",
        "parrySaves": "0",
        "passattempts": "31",
        "passesmade": "24",
        "pos": "midfielder",
        "punchSaves": "0",
        "rating": "7.10",
        "realtimegame": "887",
        "realtimeidle": "16",
        "redcards": "0",
        "reflexSaves": "0",
        "saves": "0",
        "SCORE": "1",
        "secondsPlayed": "5468",
        "shots": "2",
        "tackleattempts": "6",
        "tacklesmade": "0",
        "userResult": "0",
        "vproattr": "NH",
        "vprohackreason": "0",
        "wins": "0",
        "playername": "STR1KE9444"
      },
      "1725617121": {
        "archetypeid": "10",
        "assists": "0",
        "ballDiveSaves": "0",
        "cleansheetsany": "0",
        "cleansheetsdef": "0",
        "cleansheetsgk": "0",
        "crossSaves": "0",
        "gameTime": "5468",
        "goals": "0",
        "goalsconceded": "1",
        "goodDirectionSaves": "0",
        "losses": "0",
        "match_event_aggregate_0": "0:2,100:2,101:2,102:17,103:3,105:1,106:1,107:5,108:3,109:2,111:6,112:3,121:2,142:1,143:10,147:1,152:2,164:2,174:20,175:11,176:11,177:2,178:3,179:1,181:1,182:8,183:2,207:1,211:1,212:3,215:26,216:4,219:25,229:2,24:20,26:6,265:1,27:2,29:1,30:6,31:2",
        "match_event_aggregate_1": "32:12,34:8,35:1,6:3,8:1,97:19,98:1,99:1",
        "match_event_aggregate_2": "",
        "match_event_aggregate_3": "",
        "mom": "0",
        "namespace": "1",
        "parrySaves": "0",
        "passattempts": "30",
        "passesmade": "26",
        "pos": "midfielder",
        "punchSaves": "0",
        "rating": "7.40",
        "realtimegame": "887",
        "realtimeidle": "4",
        "redcards": "0",
        "reflexSaves": "0",
        "saves": "0",
        "SCORE": "1",
        "secondsPlayed": "5468",
        "shots": "0",
        "tackleattempts": "2",
        "tacklesmade": "2",
        "userResult": "0",
        "vproattr": "NH",
        "vprohackreason": "0",
        "wins": "0",
        "playername": "EasyMoneyDre1"
      }
    },
    "127516": {
      "997248436": {
        "archetypeid": "4",
        "assists": "0",
        "ballDiveSaves": "0",
        "cleansheetsany": "0",
        "cleansheetsdef": "0",
        "cleansheetsgk": "0",
        "crossSaves": "0",
        "gameTime": "5468",
        "goals": "0",
        "goalsconceded": "1",
        "goodDirectionSaves": "0",
        "losses": "0",
        "match_event_aggregate_0": "0:2,10:1,108:3,111:47,112:1,121:2,143:2,152:1,158:1,162:1,164:2,174:13,175:3,176:6,182:5,184:1,215:11,216:4,229:2,24:4,25:2,26:5,266:1,27:1,28:2,30:8,31:1,32:2,33:1,34:1,35:1,5:1,6:3,9:1,97:7",
        "match_event_aggregate_1": "",
        "match_event_aggregate_2": "",
        "match_event_aggregate_3": "",
        "mom": "1",
        "namespace": "2",
        "parrySaves": "0",
        "passattempts": "16",
        "passesmade": "11",
        "pos": "defender",
        "punchSaves": "0",
        "rating": "8.10",
        "realtimegame": "887",
        "realtimeidle": "1",
        "redcards": "0",
        "reflexSaves": "0",
        "saves": "0",
        "SCORE": "1",
        "secondsPlayed": "5468",
        "shots": "0",
        "tackleattempts": "3",
        "tacklesmade": "2",
        "userResult": "0",
        "vproattr": "NH",
        "vprohackreason": "0",
        "wins": "0",
        "playername": "TubbierMussel92"
      },
      "1277951868": {
        "archetypeid": "11",
        "assists": "1",
        "ballDiveSaves": "0",
        "cleansheetsany": "0",
        "cleansheetsdef": "0",
        "cleansheetsgk": "0",
        "crossSaves": "0",
        "gameTime": "5468",
        "goals": "0",
        "goalsconceded": "1",
        "goodDirectionSaves": "0",
        "losses": "0",
        "match_event_aggregate_0": "1:1,100:1,101:1,102:2,103:29,106:1,107:5,11:1,110:1,112:5,114:1,118:1,14:1,143:2,151:3,152:3,174:11,175:7,176:3,177:3,178:3,182:4,183:2,19:1,195:1,196:1,200:1,21:1,211:1,212:4,215:8,216:5,218:2,219:34,24:5,25:2,26:3,265:1,27:3,30:4,31:4,32:1,34:3",
        "match_event_aggregate_1": "35:1,6:1,97:12,99:1",
        "match_event_aggregate_2": "",
        "match_event_aggregate_3": "",
        "mom": "0",
        "namespace": "1",
        "parrySaves": "0",
        "passattempts": "13",
        "passesmade": "8",
        "pos": "forward",
        "punchSaves": "0",
        "rating": "6.30",
        "realtimegame": "887",
        "realtimeidle": "16",
        "redcards": "0",
        "reflexSaves": "0",
        "saves": "0",
        "SCORE": "1",
        "secondsPlayed": "5468",
        "shots": "2",
        "tackleattempts": "3",
        "tacklesmade": "0",
        "userResult": "0",
        "vproattr": "NH",
        "vprohackreason": "0",
        "wins": "0",
        "playername": "ValsaynViking"
      },
      "1694071402": {
        "archetypeid": "12",
        "assists": "0",
        "ballDiveSaves": "0",
        "cleansheetsany": "0",
        "cleansheetsdef": "0",
        "cleansheetsgk": "0",
        "crossSaves": "0",
        "gameTime": "5468",
        "goals": "1",
        "goalsconceded": "1",
        "goodDirectionSaves": "0",
        "losses": "0",
        "match_event_aggregate_0": "0:1,101:8,102:17,106:1,107:1,108:1,109:1,111:9,112:2,114:1,121:1,13:1,131:1,137:1,14:1,145:1,151:2,152:3,157:1,158:1,164:1,174:15,175:4,176:4,177:4,178:1,18:1,182:4,183:2,186:1,211:4,214:1,215:9,216:6,217:2,218:1,219:26,229:1,24:8,25:2,26:1,27:3,30:4",
        "match_event_aggregate_1": "31:4,32:4,34:1,35:2,37:1,6:2,97:12,99:1",
        "match_event_aggregate_2": "",
        "match_event_aggregate_3": "",
        "mom": "0",
        "namespace": "1",
        "parrySaves": "0",
        "passattempts": "15",
        "passesmade": "9",
        "pos": "forward",
        "punchSaves": "0",
        "rating": "7.40",
        "realtimegame": "887",
        "realtimeidle": "6",
        "redcards": "0",
        "reflexSaves": "0",
        "saves": "0",
        "SCORE": "1",
        "secondsPlayed": "5468",
        "shots": "3",
        "tackleattempts": "1",
        "tacklesmade": "1",
        "userResult": "0",
        "vproattr": "NH",
        "vprohackreason": "0",
        "wins": "0",
        "playername": "Mvaldez2611"
      },
      "1008454114921": {
        "archetypeid": "9",
        "assists": "0",
        "ballDiveSaves": "0",
        "cleansheetsany": "0",
        "cleansheetsdef": "0",
        "cleansheetsgk": "0",
        "crossSaves": "0",
        "gameTime": "5468",
        "goals": "0",
        "goalsconceded": "1",
        "goodDirectionSaves": "0",
        "losses": "0",
        "match_event_aggregate_0": "0:1,1:6,100:2,101:2,102:1,103:49,107:1,111:1,112:1,114:1,121:1,13:1,151:1,152:5,158:1,163:1,164:1,174:9,175:4,176:1,177:2,182:3,183:1,202:1,212:1,215:6,216:3,217:1,219:55,229:1,24:2,25:1,26:3,28:1,29:2,30:5,31:3,34:1,97:8,99:1",
        "match_event_aggregate_1": "",
        "match_event_aggregate_2": "",
        "match_event_aggregate_3": "",
        "mom": "0",
        "namespace": "1",
        "parrySaves": "0",
        "passattempts": "9",
        "passesmade": "6",
        "pos": "forward",
        "punchSaves": "0",
        "rating": "6.30",
        "realtimegame": "887",
        "realtimeidle": "9",
        "redcards": "0",
        "reflexSaves": "0",
        "saves": "0",
        "SCORE": "1",
        "secondsPlayed": "5468",
        "shots": "1",
        "tackleattempts": "7",
        "tacklesmade": "1",
        "userResult": "0",
        "vproattr": "NH",
        "vprohackreason": "0",
        "wins": "0",
        "playername": "moeagle445"
      }
    }
  },
  "aggregate": {
    "727011": {
      "archetypeid": 33,
      "assists": 0,
      "ballDiveSaves": 0,
      "cleansheetsany": 0,
      "cleansheetsdef": 0,
      "cleansheetsgk": 0,
      "crossSaves": 0,
      "gameTime": 16404,
      "goals": 1,
      "goalsconceded": 3,
      "goodDirectionSaves": 0,
      "losses": 0,
      "match_event_aggregate_0": 0,
      "match_event_aggregate_1": 0,
      "match_event_aggregate_2": 0,
      "match_event_aggregate_3": 0,
      "mom": 0,
      "namespace": 4,
      "parrySaves": 0,
      "passattempts": 81,
      "passesmade": 67,
      "pos": 0,
      "punchSaves": 0,
      "rating": 22.0,
      "realtimegame": 2661,
      "realtimeidle": 32,
      "redcards": 0,
      "reflexSaves": 0,
      "saves": 0,
      "SCORE": 3,
      "secondsPlayed": 16404,
      "shots": 4,
      "tackleattempts": 12,
      "tacklesmade": 2,
      "userResult": 0,
      "vproattr": 0,
      "vprohackreason": 0,
      "wins": 0
    },
    "127516": {
      "archetypeid": 36,
      "assists": 1,
      "ballDiveSaves": 0,
      "cleansheetsany": 0,
      "cleansheetsdef": 0,
      "cleansheetsgk": 0,
      "crossSaves": 0,
      "gameTime": 21872,
      "goals": 1,
      "goalsconceded": 4,
      "goodDirectionSaves": 0,
      "losses": 0,
      "match_event_aggregate_0": 0,
      "match_event_aggregate_1": 0,
      "match_event_aggregate_2": 0,
      "match_event_aggregate_3": 0,
      "mom": 1,
      "namespace": 5,
      "parrySaves": 0,
      "passattempts": 53,
      "passesmade": 34,
      "pos": 0,
      "punchSaves": 0,
      "rating": 28.1,
      "realtimegame": 3548,
      "realtimeidle": 32,
      "redcards": 0,
      "reflexSaves": 0,
      "saves": 0,
      "SCORE": 4,
      "secondsPlayed": 21872,
      "shots": 6,
      "tackleattempts": 14,
      "tacklesmade": 4,
      "userResult": 0,
      "vproattr": 0,
      "vprohackreason": 0,
      "wins": 0
    }
  }
}